aiy_log/__init__.py
aiy_log/log.py
aiy_scheduler/__init__.py
aiy_scheduler/rwlock.py
aiy_scheduler/scheduler.py
pyaiy-0.1.6.dist-info/METADATA
pyaiy-0.1.6.dist-info/WHEEL
pyaiy-0.1.6.dist-info/top_level.txt
pyaiy-0.1.6.dist-info/RECORD
