Metadata-Version: 2.1
Name: pyaiy
Version: 0.1.6
Summary: aiy
Home-page: UNKNOWN
License: UNKNOWN
Platform: UNKNOWN
